{
  "4644070": {
    "alternate_no": [],
    "attempted_parts": [
      {
        "confidence": 1.0,
        "generated_from": "98393",
        "part_file": "98393.dat",
        "resolution_type": "exact",
        "source": "bricklink_canonical"
      },
      {
        "confidence": 0.99,
        "generated_from": "98393",
        "part_file": "bl_98393.dat",
        "resolution_type": "alias",
        "source": "generated_bl_alias"
      }
    ],
    "bricklink_color_id": 152,
    "bricklink_name": "Friends Accessories, Medical, 10 in Bag &#40;Multipack&#41;",
    "bricklink_part": "98393",
    "lego_name": "ACCESSORIES, MEDICAL",
    "original_part": "98393",
    "reject_reason": "unresolved",
    "resolution_candidates": [
      "98393"
    ],
    "studio_color_id": 323,
    "timestamp": 1779869409.3703277
  },
  "6103444": {
    "alternate_no": [],
    "attempted_parts": [
      {
        "confidence": 1.0,
        "generated_from": "11402",
        "part_file": "11402.dat",
        "resolution_type": "exact",
        "source": "bricklink_canonical"
      },
      {
        "confidence": 0.99,
        "generated_from": "11402",
        "part_file": "bl_11402.dat",
        "resolution_type": "alias",
        "source": "generated_bl_alias"
      }
    ],
    "bricklink_color_id": 95,
    "bricklink_name": "Minifigure, Utensil Tools, 9 in Bag &#40;Multipack&#41;",
    "bricklink_part": "11402",
    "lego_name": "TOOL WHEEL",
    "original_part": "11402",
    "reject_reason": "unresolved",
    "resolution_candidates": [
      "11402"
    ],
    "studio_color_id": 179,
    "timestamp": 1779869409.655823
  },
  "6236464": {
    "alternate_no": [],
    "attempted_parts": [
      {
        "confidence": 1.0,
        "generated_from": "85489",
        "part_file": "85489.dat",
        "resolution_type": "exact",
        "source": "bricklink_canonical"
      },
      {
        "confidence": 0.99,
        "generated_from": "85489",
        "part_file": "bl_85489.dat",
        "resolution_type": "alias",
        "source": "generated_bl_alias"
      }
    ],
    "bricklink_color_id": 11,
    "bricklink_name": "Train Wheel RC, Spoked with Technic Axle Hole and Counterweight, Blind and Flanged Driver, 3 in Bag &#40;Multipack&#41;",
    "bricklink_part": "85489",
    "lego_name": "3 TRAIN WHEEL \u00d830 M+U FLANGE",
    "original_part": "85489",
    "reject_reason": "unresolved",
    "resolution_candidates": [
      "85489"
    ],
    "studio_color_id": 0,
    "timestamp": 1779869409.14858
  },
  "6294243": {
    "alternate_no": [],
    "attempted_parts": [
      {
        "confidence": 1.0,
        "generated_from": "36451",
        "part_file": "36451.dat",
        "resolution_type": "exact",
        "source": "bricklink_canonical"
      },
      {
        "confidence": 0.99,
        "generated_from": "36451",
        "part_file": "bl_36451.dat",
        "resolution_type": "alias",
        "source": "generated_bl_alias"
      }
    ],
    "bricklink_color_id": 19,
    "bricklink_name": "Rock Faceted with Small Pin &#40;Marvel Infinity Stone&#41;, 4 on Sprue",
    "bricklink_part": "36451",
    "lego_name": "DIAMOND, W/1,5 SHAFT",
    "original_part": "36451",
    "reject_reason": "unresolved",
    "resolution_candidates": [
      "36451"
    ],
    "studio_color_id": 46,
    "timestamp": 1779869408.9278502
  },
  "6445944": {
    "alternate_no": [],
    "attempted_parts": [
      {
        "confidence": 1.0,
        "generated_from": "92355",
        "part_file": "92355.dat",
        "resolution_type": "exact",
        "source": "bricklink_canonical"
      },
      {
        "confidence": 0.99,
        "generated_from": "92355",
        "part_file": "bl_92355.dat",
        "resolution_type": "alias",
        "source": "generated_bl_alias"
      }
    ],
    "bricklink_color_id": 71,
    "bricklink_name": "Friends Accessories, Animal Show and Grooming Supplies, 16 in Bag &#40;Multipack&#41;",
    "bricklink_part": "92355",
    "lego_name": "ACCEC, ANIMAL W.SHAFT 1,5/3,2",
    "original_part": "92355",
    "reject_reason": "unresolved",
    "resolution_candidates": [
      "92355"
    ],
    "studio_color_id": 26,
    "timestamp": 1779869408.707961
  },
  "6545848": {
    "alternate_no": [],
    "attempted_parts": [
      {
        "confidence": 1.0,
        "generated_from": "49595",
        "part_file": "49595.dat",
        "resolution_type": "exact",
        "source": "bricklink_canonical"
      },
      {
        "confidence": 0.99,
        "generated_from": "49595",
        "part_file": "bl_49595.dat",
        "resolution_type": "alias",
        "source": "generated_bl_alias"
      }
    ],
    "bricklink_color_id": 236,
    "bricklink_name": "Friends Accessories, Marine Life, 12 in Bag &#40;Multipack&#41;",
    "bricklink_part": "49595",
    "lego_name": "ACCESSORIES, MARINE LIFE, NO. 1",
    "original_part": "49595",
    "reject_reason": "unresolved",
    "resolution_candidates": [
      "49595"
    ],
    "studio_color_id": 368,
    "timestamp": 1779869408.4800742
  }
}
